dmklr/__init__.py
dmklr/dmklr.py
dmklr-0.1.dist-info/METADATA
dmklr-0.1.dist-info/WHEEL
dmklr-0.1.dist-info/top_level.txt
dmklr-0.1.dist-info/RECORD
