Metadata-Version: 2.1
Name: dmklr
Version: 0.1
Summary: The Goal Of This Library Is To Help Students To Learn Data Mining
Home-page: UNKNOWN
Author: UNKNOWN
Author-email: UNKNOWN
License: UNKNOWN
Platform: UNKNOWN
